{
  "books": [
  {
    "identifier": "karinaahi200000mnka",
    "title": "Kari Naahi 20",
    "author": "M.N. Kamath",
    "publisher": "Prabhat Printers, Ltd., Mangalore",
    "info": "",
    "tags": "ಒಂದಾಣೆ ಮಾಲೆ, ಕನ್ನಡ ಸಾಹಿತ್ಯ",
    "level": "Kannada Literature",
    "authorUrl": "https://archive.org/search.php?query=creator%3AKari Naahi 20",
    "url": "https://archive.org/details/karinaahi200000mnka",
    "cover": "https://archive.org/services/img/karinaahi200000mnka"
  },
  {
    "identifier": "babigebasinga150000kudp",
    "title": "Babige Basinga 15",
    "author": "Kudpi Vasudev Shenoy",
    "publisher": "Prabhat Printers, Ltd., Mangalore",
    "info": "",
    "tags": "ಒಂದಾಣೆ ಮಾಲೆ, ಕನ್ನಡ ಸಾಹಿತ್ಯ",
    "level": "Kannada Literature",
    "authorUrl": "https://archive.org/search.php?query=creator%3ABabige Basinga 15",
    "url": "https://archive.org/details/babigebasinga150000kudp",
    "cover": "https://archive.org/services/img/babigebasinga150000kudp"
  },
  {
    "identifier": "rathothsava190000unse",
    "title": "Rathothsava 19",
    "author": "",
    "publisher": "Prabhat Printers, Ltd., Mangalore",
    "info": "",
    "tags": "ಒಂದಾಣೆ ಮಾಲೆ, ಕನ್ನಡ ಸಾಹಿತ್ಯ",
    "level": "Kannada Literature",
    "authorUrl": "https://archive.org/search.php?query=creator%3ARathothsava 19",
    "url": "https://archive.org/details/rathothsava190000unse",
    "cover": "https://archive.org/services/img/rathothsava190000unse"
  },
  {
    "identifier": "tissuehoshadhaga0000srip",
    "title": "Tissue Hoshadhagala Kaipidi (A Handbook Of Tissue Remedies) 10",
    "author": "Sri. P.S. Venkatakrishna Rao, M.A., B.T.",
    "publisher": "Prabhat Printers, Ltd., Mangaloreq",
    "info": "",
    "tags": "ಒಂದಾಣೆ ಮಾಲೆ, ಕನ್ನಡ ಸಾಹಿತ್ಯ",
    "level": "Kannada Literature",
    "authorUrl": "https://archive.org/search.php?query=creator%3ATissue Hoshadhagala Kaipidi (A Handbook Of Tissue Remedies) 10",
    "url": "https://archive.org/details/tissuehoshadhaga0000srip",
    "cover": "https://archive.org/services/img/tissuehoshadhaga0000srip"
  },
  {
    "identifier": "bharathadamahana0000srit_f5j0",
    "title": "Bharathada Mahanagaragalu 24",
    "author": "Sri. T. Chandraraja Setty",
    "publisher": "Prabhat Printers, Ltd., Mangalore",
    "info": "",
    "tags": "ಒಂದಾಣೆ ಮಾಲೆ, ಕನ್ನಡ ಸಾಹಿತ್ಯ",
    "level": "Kannada Literature",
    "authorUrl": "https://archive.org/search.php?query=creator%3ABharathada Mahanagaragalu 24",
    "url": "https://archive.org/details/bharathadamahana0000srit_f5j0",
    "cover": "https://archive.org/services/img/bharathadamahana0000srit_f5j0"
  },
  {
    "identifier": "srikeshtradharma0000unse",
    "title": "Sri Keshtra Dharmasthala 11",
    "author": "",
    "publisher": "Prabhat Printers, Ltd., Mangalore",
    "info": "",
    "tags": "ಒಂದಾಣೆ ಮಾಲೆ, ಕನ್ನಡ ಸಾಹಿತ್ಯ",
    "level": "Kannada Literature",
    "authorUrl": "https://archive.org/search.php?query=creator%3ASri Keshtra Dharmasthala 11",
    "url": "https://archive.org/details/srikeshtradharma0000unse",
    "cover": "https://archive.org/services/img/srikeshtradharma0000unse"
  },
  {
    "identifier": "kalanigesambavan0000unse",
    "title": "Kalanige Sambavane Mathu Ithara Kathegalu 3",
    "author": "",
    "publisher": "Prabhat Printers, Ltd., Mangalore",
    "info": "",
    "tags": "ಒಂದಾಣೆ ಮಾಲೆ, ಕನ್ನಡ ಸಾಹಿತ್ಯ",
    "level": "Kannada Literature",
    "authorUrl": "https://archive.org/search.php?query=creator%3AKalanige Sambavane Mathu Ithara Kathegalu 3",
    "url": "https://archive.org/details/kalanigesambavan0000unse",
    "cover": "https://archive.org/services/img/kalanigesambavan0000unse"
  },
  {
    "identifier": "abharanagalapeti0000srib",
    "title": "Abharanagala Petige Mathu Ethara Kathegalu 40",
    "author": "Sri Balkuru Subraya Adiga",
    "publisher": "Prabhat Printers, Ltd., Mangalore",
    "info": "",
    "tags": "ಒಂದಾಣೆ ಮಾಲೆ, ಕನ್ನಡ ಸಾಹಿತ್ಯ",
    "level": "Kannada Literature",
    "authorUrl": "https://archive.org/search.php?query=creator%3AAbharanagala Petige Mathu Ethara Kathegalu 40",
    "url": "https://archive.org/details/abharanagalapeti0000srib",
    "cover": "https://archive.org/services/img/abharanagalapeti0000srib"
  },
  {
    "identifier": "veeraramanikarma0000srik",
    "title": "Veeraramani Karma Devi 56",
    "author": "Sri K. S. Sharma",
    "publisher": "Prabhat Printers, Ltd., Mangalore",
    "info": "",
    "tags": "ಒಂದಾಣೆ ಮಾಲೆ, ಕನ್ನಡ ಸಾಹಿತ್ಯ",
    "level": "Kannada Literature",
    "authorUrl": "https://archive.org/search.php?query=creator%3AVeeraramani Karma Devi 56",
    "url": "https://archive.org/details/veeraramanikarma0000srik",
    "cover": "https://archive.org/services/img/veeraramanikarma0000srik"
  },
  {
    "identifier": "kuraalthiruvallu0000srid",
    "title": "Kuraal Thiruvallur Mahakavi Virachitha Subhashitha 22",
    "author": "Sri. D. PuttaSwamy",
    "publisher": "Prabhat Printers, Ltd., Mangalore",
    "info": "",
    "tags": "ಒಂದಾಣೆ ಮಾಲೆ, ಕನ್ನಡ ಸಾಹಿತ್ಯ",
    "level": "Kannada Literature",
    "authorUrl": "https://archive.org/search.php?query=creator%3AKuraal Thiruvallur Mahakavi Virachitha Subhashitha 22",
    "url": "https://archive.org/details/kuraalthiruvallu0000srid",
    "cover": "https://archive.org/services/img/kuraalthiruvallu0000srid"
  },
  {
    "identifier": "dharshanadakathe0000tsha",
    "title": "Dharshanada Kathegalu 33",
    "author": "T. Shankar Bhat And B.M. Sharma",
    "publisher": "Prabhat Printers, Ltd., Mangalore",
    "info": "",
    "tags": "ಒಂದಾಣೆ ಮಾಲೆ, ಕನ್ನಡ ಸಾಹಿತ್ಯ",
    "level": "Kannada Literature",
    "authorUrl": "https://archive.org/search.php?query=creator%3ADharshanada Kathegalu 33",
    "url": "https://archive.org/details/dharshanadakathe0000tsha",
    "cover": "https://archive.org/services/img/dharshanadakathe0000tsha"
  },
  {
    "identifier": "bharathadamantri0000unse",
    "title": "Bharathada Mantrimandalagalu 41",
    "author": "",
    "publisher": "Prabhat Printers, Ltd., Mangalore",
    "info": "",
    "tags": "ಒಂದಾಣೆ ಮಾಲೆ, ಕನ್ನಡ ಸಾಹಿತ್ಯ",
    "level": "Kannada Literature",
    "authorUrl": "https://archive.org/search.php?query=creator%3ABharathada Mantrimandalagalu 41",
    "url": "https://archive.org/details/bharathadamantri0000unse",
    "cover": "https://archive.org/services/img/bharathadamantri0000unse"
  },
  {
    "identifier": "gumanikaviyaupad0000sria",
    "title": "Gumanikaviya Upadesha Shathaka 36",
    "author": "Sri Ammembala Ananthaya Navada",
    "publisher": "Prabhat Printers, Ltd., Mangalore",
    "info": "",
    "tags": "ಒಂದಾಣೆ ಮಾಲೆ, ಕನ್ನಡ ಸಾಹಿತ್ಯ",
    "level": "Kannada Literature",
    "authorUrl": "https://archive.org/search.php?query=creator%3AGumanikaviya Upadesha Shathaka 36",
    "url": "https://archive.org/details/gumanikaviyaupad0000sria",
    "cover": "https://archive.org/services/img/gumanikaviyaupad0000sria"
  },
  {
    "identifier": "akandathandava470000srib",
    "title": "Akanda Thandava 47",
    "author": "Sri B. Damodara Balega",
    "publisher": "Prabhat Printers, Ltd., Mangalore",
    "info": "",
    "tags": "ಒಂದಾಣೆ ಮಾಲೆ, ಕನ್ನಡ ಸಾಹಿತ್ಯ",
    "level": "Kannada Literature",
    "authorUrl": "https://archive.org/search.php?query=creator%3AAkanda Thandava 47",
    "url": "https://archive.org/details/akandathandava470000srib",
    "cover": "https://archive.org/services/img/akandathandava470000srib"
  },
  {
    "identifier": "adbhuthatyagamat0000vaid",
    "title": "Adbhutha Tyaga Mathu Kirugathegalu 5",
    "author": "Vaidyaguru M.R. Bhat",
    "publisher": "Prabhat Printers, Ltd., Mangalore",
    "info": "",
    "tags": "ಒಂದಾಣೆ ಮಾಲೆ, ಕನ್ನಡ ಸಾಹಿತ್ಯ",
    "level": "Kannada Literature",
    "authorUrl": "https://archive.org/search.php?query=creator%3AAdbhutha Tyaga Mathu Kirugathegalu 5",
    "url": "https://archive.org/details/adbhuthatyagamat0000vaid",
    "cover": "https://archive.org/services/img/adbhuthatyagamat0000vaid"
  },
  {
    "identifier": "venkatanasankata0000drsp",
    "title": "Venkatana Sankata And Doctor ra Visit 14",
    "author": "Dr. S.P.Bhat And M.N. Kamat",
    "publisher": "Prabhat Printers, Ltd., Mangalore",
    "info": "",
    "tags": "ಒಂದಾಣೆ ಮಾಲೆ, ಕನ್ನಡ ಸಾಹಿತ್ಯ",
    "level": "Kannada Literature",
    "authorUrl": "https://archive.org/search.php?query=creator%3AVenkatana Sankata And Doctor ra Visit 14",
    "url": "https://archive.org/details/venkatanasankata0000drsp",
    "cover": "https://archive.org/services/img/venkatanasankata0000drsp"
  },
  {
    "identifier": "subhashitha450000srim",
    "title": "Subhashitha 45",
    "author": "Sri M.Subrayan, Vidhvan",
    "publisher": "Prabhat Printers, Ltd., Mangalore",
    "info": "",
    "tags": "ಒಂದಾಣೆ ಮಾಲೆ, ಕನ್ನಡ ಸಾಹಿತ್ಯ",
    "level": "Kannada Literature",
    "authorUrl": "https://archive.org/search.php?query=creator%3ASubhashitha 45",
    "url": "https://archive.org/details/subhashitha450000srim",
    "cover": "https://archive.org/services/img/subhashitha450000srim"
  },
  {
    "identifier": "sadrisubbha40000mnka",
    "title": "Sadri Subbha 4",
    "author": "M.N. Kamath",
    "publisher": "Prabhat Printers, Ltd., Mangalore",
    "info": "",
    "tags": "ಒಂದಾಣೆ ಮಾಲೆ, ಕನ್ನಡ ಸಾಹಿತ್ಯ",
    "level": "Kannada Literature",
    "authorUrl": "https://archive.org/search.php?query=creator%3ASadri Subbha 4",
    "url": "https://archive.org/details/sadrisubbha40000mnka",
    "cover": "https://archive.org/services/img/sadrisubbha40000mnka"
  },
  {
    "identifier": "bharathadamahana0000srit",
    "title": "Bharathada Mahanagaragalu 21",
    "author": "Sri. T. Chandraraja Setty",
    "publisher": "Prabhat Printers, Ltd., Mangalore",
    "info": "",
    "tags": "ಒಂದಾಣೆ ಮಾಲೆ, ಕನ್ನಡ ಸಾಹಿತ್ಯ",
    "level": "Kannada Literature",
    "authorUrl": "https://archive.org/search.php?query=creator%3ABharathada Mahanagaragalu 21",
    "url": "https://archive.org/details/bharathadamahana0000srit",
    "cover": "https://archive.org/services/img/bharathadamahana0000srit"
  },
  {
    "identifier": "suryanasamsaaram0000bsha",
    "title": "Suryana Samsaara Mathu Ethara Kathegalu 23",
    "author": "B. Shankar Bhat",
    "publisher": "Prabhat Printers, Ltd., Mangalore",
    "info": "",
    "tags": "ಒಂದಾಣೆ ಮಾಲೆ, ಕನ್ನಡ ಸಾಹಿತ್ಯ",
    "level": "Kannada Literature",
    "authorUrl": "https://archive.org/search.php?query=creator%3ASuryana Samsaara Mathu Ethara Kathegalu 23",
    "url": "https://archive.org/details/suryanasamsaaram0000bsha",
    "cover": "https://archive.org/services/img/suryanasamsaaram0000bsha"
  },
  {
    "identifier": "jagalaganntamath0000vaid",
    "title": "Jagalagannta Mathu Ethara Kathegalu 18",
    "author": "Vaidyaguru M.R. Bhat",
    "publisher": "Prabhat Printers, Ltd., Mangalore",
    "info": "",
    "tags": "ಒಂದಾಣೆ ಮಾಲೆ, ಕನ್ನಡ ಸಾಹಿತ್ಯ",
    "level": "Kannada Literature",
    "authorUrl": "https://archive.org/search.php?query=creator%3AJagalagannta Mathu Ethara Kathegalu 18",
    "url": "https://archive.org/details/jagalaganntamath0000vaid",
    "cover": "https://archive.org/services/img/jagalaganntamath0000vaid"
  },
  {
    "identifier": "maaraavathaara260000srig",
    "title": "Maaraavathaara 26",
    "author": "Sri. G. R. Pandeshvara",
    "publisher": "Prabhat Printers, Ltd., Mangalore",
    "info": "",
    "tags": "ಒಂದಾಣೆ ಮಾಲೆ, ಕನ್ನಡ ಸಾಹಿತ್ಯ",
    "level": "Kannada Literature",
    "authorUrl": "https://archive.org/search.php?query=creator%3AMaaraavathaara 26",
    "url": "https://archive.org/details/maaraavathaara260000srig",
    "cover": "https://archive.org/services/img/maaraavathaara260000srig"
  },
  {
    "identifier": "meerabhai550000sris",
    "title": "Meera Bhai 55",
    "author": "Sri Sam. Ja. Rao",
    "publisher": "Prabhat Printers, Ltd., Mangalore",
    "info": "",
    "tags": "ಒಂದಾಣೆ ಮಾಲೆ, ಕನ್ನಡ ಸಾಹಿತ್ಯ",
    "level": "Kannada Literature",
    "authorUrl": "https://archive.org/search.php?query=creator%3AMeera Bhai 55",
    "url": "https://archive.org/details/meerabhai550000sris",
    "cover": "https://archive.org/services/img/meerabhai550000sris"
  },
  {
    "identifier": "bharathadanalkuk0000srit",
    "title": "Bharathada Nalku Kalashagalu 43",
    "author": "Sri T. Chandraraja Shetty",
    "publisher": "Prabhat Printers, Ltd., Mangalore",
    "info": "",
    "tags": "ಒಂದಾಣೆ ಮಾಲೆ, ಕನ್ನಡ ಸಾಹಿತ್ಯ",
    "level": "Kannada Literature",
    "authorUrl": "https://archive.org/search.php?query=creator%3ABharathada Nalku Kalashagalu 43",
    "url": "https://archive.org/details/bharathadanalkuk0000srit",
    "cover": "https://archive.org/services/img/bharathadanalkuk0000srit"
  },
  {
    "identifier": "aluvinaholyemath0000nava",
    "title": "Aluvina Holye Mathu Keshava Bhoopa 34",
    "author": "Navagirinanda",
    "publisher": "Prabhat Printers, Ltd., Mangalore",
    "info": "",
    "tags": "ಒಂದಾಣೆ ಮಾಲೆ, ಕನ್ನಡ ಸಾಹಿತ್ಯ",
    "level": "Kannada Literature",
    "authorUrl": "https://archive.org/search.php?query=creator%3AAluvina Holye Mathu Keshava Bhoopa 34",
    "url": "https://archive.org/details/aluvinaholyemath0000nava",
    "cover": "https://archive.org/services/img/aluvinaholyemath0000nava"
  },
  {
    "identifier": "1857rasipayidhan0000srik",
    "title": "1857 Ra \"Sipayi Dhangye\" 46",
    "author": "Sri K.Subashchandra Shenoy",
    "publisher": "Prabhat Printers, Ltd., Mangalore",
    "info": "",
    "tags": "ಒಂದಾಣೆ ಮಾಲೆ, ಕನ್ನಡ ಸಾಹಿತ್ಯ",
    "level": "Kannada Literature",
    "authorUrl": "https://archive.org/search.php?query=creator%3A1857 Ra \"Sipayi Dhangye\" 46",
    "url": "https://archive.org/details/1857rasipayidhan0000srik",
    "cover": "https://archive.org/services/img/1857rasipayidhan0000srik"
  },
  {
    "identifier": "karkaladacharitr0000dput",
    "title": "Karkalada Charitre 31",
    "author": "D. Puttaswamy",
    "publisher": "Prabhat Printers, Ltd., Mangalore",
    "info": "",
    "tags": "ಒಂದಾಣೆ ಮಾಲೆ, ಕನ್ನಡ ಸಾಹಿತ್ಯ",
    "level": "Kannada Literature",
    "authorUrl": "https://archive.org/search.php?query=creator%3AKarkalada Charitre 31",
    "url": "https://archive.org/details/karkaladacharitr0000dput",
    "cover": "https://archive.org/services/img/karkaladacharitr0000dput"
  },
  {
    "identifier": "vyasanadindalabh0000sril",
    "title": "Vyasanadinda Labha Mathu Ethara Kathegalu 44",
    "author": "Sri L.S.Nayak",
    "publisher": "Prabhat Printers, Ltd., Mangalore",
    "info": "",
    "tags": "ಒಂದಾಣೆ ಮಾಲೆ, ಕನ್ನಡ ಸಾಹಿತ್ಯ",
    "level": "Kannada Literature",
    "authorUrl": "https://archive.org/search.php?query=creator%3AVyasanadinda Labha Mathu Ethara Kathegalu 44",
    "url": "https://archive.org/details/vyasanadindalabh0000sril",
    "cover": "https://archive.org/services/img/vyasanadindalabh0000sril"
  },
  {
    "identifier": "mahathma540000sril",
    "title": "Mahathma 54",
    "author": "Sri L.S.Nayak",
    "publisher": "Prabhat Printers, Ltd., Mangalore",
    "info": "",
    "tags": "ಒಂದಾಣೆ ಮಾಲೆ, ಕನ್ನಡ ಸಾಹಿತ್ಯ",
    "level": "Kannada Literature",
    "authorUrl": "https://archive.org/search.php?query=creator%3AMahathma 54",
    "url": "https://archive.org/details/mahathma540000sril",
    "cover": "https://archive.org/services/img/mahathma540000sril"
  },
  {
    "identifier": "kalubaleyakathe40000shri",
    "title": "Kalubaleya Kathe 42",
    "author": "Shrimathi B. S. Rathanamma",
    "publisher": "Prabhat Printers, Ltd., Mangalore",
    "info": "",
    "tags": "ಒಂದಾಣೆ ಮಾಲೆ, ಕನ್ನಡ ಸಾಹಿತ್ಯ",
    "level": "Kannada Literature",
    "authorUrl": "https://archive.org/search.php?query=creator%3AKalubaleya Kathe 42",
    "url": "https://archive.org/details/kalubaleyakathe40000shri",
    "cover": "https://archive.org/services/img/kalubaleyakathe40000shri"
  },
  {
    "identifier": "sathisavithri390000pven",
    "title": "Sathi Savithri 39",
    "author": "P. Venkataramanna Bhat",
    "publisher": "Prabhat Printers, Ltd., Mangalore",
    "info": "",
    "tags": "ಒಂದಾಣೆ ಮಾಲೆ, ಕನ್ನಡ ಸಾಹಿತ್ಯ",
    "level": "Kannada Literature",
    "authorUrl": "https://archive.org/search.php?query=creator%3ASathi Savithri 39",
    "url": "https://archive.org/details/sathisavithri390000pven",
    "cover": "https://archive.org/services/img/sathisavithri390000pven"
  },
  {
    "identifier": "dharmashiksha530000srik",
    "title": "Dharma Shiksha 53",
    "author": "Sri Ko. Sha. Karanth",
    "publisher": "Prabhat Printers, Ltd., Mangalore",
    "info": "",
    "tags": "ಒಂದಾಣೆ ಮಾಲೆ, ಕನ್ನಡ ಸಾಹಿತ್ಯ",
    "level": "Kannada Literature",
    "authorUrl": "https://archive.org/search.php?query=creator%3ADharma Shiksha 53",
    "url": "https://archive.org/details/dharmashiksha530000srik",
    "cover": "https://archive.org/services/img/dharmashiksha530000srik"
  },
  {
    "identifier": "samgnyagannakosh0000drsp",
    "title": "Samgnya Gannakosha 49",
    "author": "Dr S.P. Bhat",
    "publisher": "Prabhat Printers, Ltd., Mangalore",
    "info": "",
    "tags": "ಒಂದಾಣೆ ಮಾಲೆ, ಕನ್ನಡ ಸಾಹಿತ್ಯ",
    "level": "Kannada Literature",
    "authorUrl": "https://archive.org/search.php?query=creator%3ASamgnya Gannakosha 49",
    "url": "https://archive.org/details/samgnyagannakosh0000drsp",
    "cover": "https://archive.org/services/img/samgnyagannakosh0000drsp"
  },
  {
    "identifier": "samgramashima520000sria",
    "title": "Samgrama Shima 52",
    "author": "Sri A.Go. Kinnigowle",
    "publisher": "Prabhat Printers, Ltd., Mangalore",
    "info": "",
    "tags": "ಒಂದಾಣೆ ಮಾಲೆ, ಕನ್ನಡ ಸಾಹಿತ್ಯ",
    "level": "Kannada Literature",
    "authorUrl": "https://archive.org/search.php?query=creator%3ASamgrama Shima 52",
    "url": "https://archive.org/details/samgramashima520000sria",
    "cover": "https://archive.org/services/img/samgramashima520000sria"
  },
  {
    "identifier": "sharabhinaseepay0000balk",
    "title": "Sharabhina Seepayegalu 35",
    "author": "Balkuru Subraya Adiga",
    "publisher": "Prabhat Printers, Ltd., Mangalore",
    "info": "",
    "tags": "ಒಂದಾಣೆ ಮಾಲೆ, ಕನ್ನಡ ಸಾಹಿತ್ಯ",
    "level": "Kannada Literature",
    "authorUrl": "https://archive.org/search.php?query=creator%3ASharabhina Seepayegalu 35",
    "url": "https://archive.org/details/sharabhinaseepay0000balk",
    "cover": "https://archive.org/services/img/sharabhinaseepay0000balk"
  },
  {
    "identifier": "lanchakesanchaka0000drsp",
    "title": "Lanchake Sanchakaara Mathu Ethara Vinodha Kathaanakagalu 9",
    "author": "Dr. S.P. Bhat",
    "publisher": "Prabhat Printers, Ltd., Mangalore",
    "info": "",
    "tags": "ಒಂದಾಣೆ ಮಾಲೆ, ಕನ್ನಡ ಸಾಹಿತ್ಯ",
    "level": "Kannada Literature",
    "authorUrl": "https://archive.org/search.php?query=creator%3ALanchake Sanchakaara Mathu Ethara Vinodha Kathaanakagalu 9",
    "url": "https://archive.org/details/lanchakesanchaka0000drsp",
    "cover": "https://archive.org/services/img/lanchakesanchaka0000drsp"
  },
  {
    "identifier": "ogatugalu170000tcha",
    "title": "Ogatugalu 17",
    "author": "T. Chandraraja Setty",
    "publisher": "Prabhat Printers, Ltd., Mangalore",
    "info": "",
    "tags": "ಒಂದಾಣೆ ಮಾಲೆ, ಕನ್ನಡ ಸಾಹಿತ್ಯ",
    "level": "Kannada Literature",
    "authorUrl": "https://archive.org/search.php?query=creator%3AOgatugalu 17",
    "url": "https://archive.org/details/ogatugalu170000tcha",
    "cover": "https://archive.org/services/img/ogatugalu170000tcha"
  },
  {
    "identifier": "haasavilaasa270000unse",
    "title": "Haasavilaasa 27",
    "author": "",
    "publisher": "Prabhat Printers, Ltd., Mangalore",
    "info": "",
    "tags": "ಒಂದಾಣೆ ಮಾಲೆ, ಕನ್ನಡ ಸಾಹಿತ್ಯ",
    "level": "Kannada Literature",
    "authorUrl": "https://archive.org/search.php?query=creator%3AHaasavilaasa 27",
    "url": "https://archive.org/details/haasavilaasa270000unse",
    "cover": "https://archive.org/services/img/haasavilaasa270000unse"
  },
  {
    "identifier": "dharmasankataath0000srit",
    "title": "Dharmasankata Athava Karna 202",
    "author": "Sri Tadhasale Vigneshwara Sharma",
    "publisher": "Prabhat Printers, Ltd., Mangalore",
    "info": "",
    "tags": "ಒಂದಾಣೆ ಮಾಲೆ, ಕನ್ನಡ ಸಾಹಿತ್ಯ",
    "level": "Kannada Literature",
    "authorUrl": "https://archive.org/search.php?query=creator%3ADharmasankata Athava Karna 202",
    "url": "https://archive.org/details/dharmasankataath0000srit",
    "cover": "https://archive.org/services/img/dharmasankataath0000srit"
  },
  {
    "identifier": "sahadevavijaya200000sria",
    "title": "Sahadeva Vijaya 207",
    "author": "Sri Aduru Balakiya Vishnaya",
    "publisher": "Prabhat Printers, Ltd., Mangalore",
    "info": "",
    "tags": "ಒಂದಾಣೆ ಮಾಲೆ, ಕನ್ನಡ ಸಾಹಿತ್ಯ",
    "level": "Kannada Literature",
    "authorUrl": "https://archive.org/search.php?query=creator%3ASahadeva Vijaya 207",
    "url": "https://archive.org/details/sahadevavijaya200000sria",
    "cover": "https://archive.org/services/img/sahadevavijaya200000sria"
  },
  {
    "identifier": "ahalyodhara2030000ambh",
    "title": "Ahalyodhara 203",
    "author": "Ambhatanaya",
    "publisher": "Prabhat Printers, Ltd., Mangalore",
    "info": "",
    "tags": "ಒಂದಾಣೆ ಮಾಲೆ, ಕನ್ನಡ ಸಾಹಿತ್ಯ",
    "level": "Kannada Literature",
    "authorUrl": "https://archive.org/search.php?query=creator%3AAhalyodhara 203",
    "url": "https://archive.org/details/ahalyodhara2030000ambh",
    "cover": "https://archive.org/services/img/ahalyodhara2030000ambh"
  },
  {
    "identifier": "uttaranapourusha0000srip",
    "title": "Uttarana Pourusha 101",
    "author": "Sri Puttana",
    "publisher": "Prabhat Printers, Ltd., Mangalore",
    "info": "",
    "tags": "ಒಂದಾಣೆ ಮಾಲೆ, ಕನ್ನಡ ಸಾಹಿತ್ಯ",
    "level": "Kannada Literature",
    "authorUrl": "https://archive.org/search.php?query=creator%3AUttarana Pourusha 101",
    "url": "https://archive.org/details/uttaranapourusha0000srip",
    "cover": "https://archive.org/services/img/uttaranapourusha0000srip"
  },
  {
    "identifier": "manushyayagna1180000srib",
    "title": "Manushya Yagna 118",
    "author": "Sri B. Shankar Bhat",
    "publisher": "Prabhat Printers, Ltd., Mangalore",
    "info": "",
    "tags": "ಒಂದಾಣೆ ಮಾಲೆ, ಕನ್ನಡ ಸಾಹಿತ್ಯ",
    "level": "Kannada Literature",
    "authorUrl": "https://archive.org/search.php?query=creator%3AManushya Yagna 118",
    "url": "https://archive.org/details/manushyayagna1180000srib",
    "cover": "https://archive.org/services/img/manushyayagna1180000srib"
  },
  {
    "identifier": "ghruhavaidhya880000srib",
    "title": "Ghruha Vaidhya 88",
    "author": "Sri Ballkuru Subraya Adiga",
    "publisher": "Prabhat Printers, Ltd., Mangalore",
    "info": "",
    "tags": "ಒಂದಾಣೆ ಮಾಲೆ, ಕನ್ನಡ ಸಾಹಿತ್ಯ",
    "level": "Kannada Literature",
    "authorUrl": "https://archive.org/search.php?query=creator%3AGhruha Vaidhya 88",
    "url": "https://archive.org/details/ghruhavaidhya880000srib",
    "cover": "https://archive.org/services/img/ghruhavaidhya880000srib"
  },
  {
    "identifier": "drbaburajendrapr0000pram",
    "title": "Dr. Babu Rajendra Prasadaru 209",
    "author": "P. Ramana Chadaga",
    "publisher": "Prabhat Printers, Ltd., Mangalore",
    "info": "",
    "tags": "ಒಂದಾಣೆ ಮಾಲೆ, ಕನ್ನಡ ಸಾಹಿತ್ಯ",
    "level": "Kannada Literature",
    "authorUrl": "https://archive.org/search.php?query=creator%3ADr. Babu Rajendra Prasadaru 209",
    "url": "https://archive.org/details/drbaburajendrapr0000pram",
    "cover": "https://archive.org/services/img/drbaburajendrapr0000pram"
  },
  {
    "identifier": "shatapathabhodha0000sriv",
    "title": "Shatapatha Bhodhamrutha 210",
    "author": "Sri Vishveshwara Sharma",
    "publisher": "Prabhat Printers, Ltd., Mangalore",
    "info": "",
    "tags": "ಒಂದಾಣೆ ಮಾಲೆ, ಕನ್ನಡ ಸಾಹಿತ್ಯ",
    "level": "Kannada Literature",
    "authorUrl": "https://archive.org/search.php?query=creator%3AShatapatha Bhodhamrutha 210",
    "url": "https://archive.org/details/shatapathabhodha0000sriv",
    "cover": "https://archive.org/services/img/shatapathabhodha0000sriv"
  },
  {
    "identifier": "sathimanisavithr0000srim",
    "title": "Sathimani Savithri 208",
    "author": "Sri M. S. Achar",
    "publisher": "Prabhat Printers, Ltd., Mangalore",
    "info": "",
    "tags": "ಒಂದಾಣೆ ಮಾಲೆ, ಕನ್ನಡ ಸಾಹಿತ್ಯ",
    "level": "Kannada Literature",
    "authorUrl": "https://archive.org/search.php?query=creator%3ASathimani Savithri 208",
    "url": "https://archive.org/details/sathimanisavithr0000srim",
    "cover": "https://archive.org/services/img/sathimanisavithr0000srim"
  },
  {
    "identifier": "mayaviniathavash0000vidh",
    "title": "Mayavini Athava Shurpanakaa Manabhanga 200",
    "author": "Vidhwan M. Gopalakrishna Bhat",
    "publisher": "Prabhat Printers, Ltd., Mangalore",
    "info": "",
    "tags": "ಒಂದಾಣೆ ಮಾಲೆ, ಕನ್ನಡ ಸಾಹಿತ್ಯ",
    "level": "Kannada Literature",
    "authorUrl": "https://archive.org/search.php?query=creator%3AMayavini Athava Shurpanakaa Manabhanga 200",
    "url": "https://archive.org/details/mayaviniathavash0000vidh",
    "cover": "https://archive.org/services/img/mayaviniathavash0000vidh"
  },
  {
    "identifier": "keralajothishapr0000vyed",
    "title": "Kerala Jothisha Pramuka Yogagalu 103",
    "author": "Vyedyaguru M. R. Bhat",
    "publisher": "Prabhat Printers, Ltd., Mangalore",
    "info": "",
    "tags": "ಒಂದಾಣೆ ಮಾಲೆ, ಕನ್ನಡ ಸಾಹಿತ್ಯ",
    "level": "Kannada Literature",
    "authorUrl": "https://archive.org/search.php?query=creator%3AKerala Jothisha Pramuka Yogagalu 103",
    "url": "https://archive.org/details/keralajothishapr0000vyed",
    "cover": "https://archive.org/services/img/keralajothishapr0000vyed"
  },
  {
    "identifier": "yakshagananataka0000srim",
    "title": "Yakshagana Natakada Parampare Mathu Kruthigalu 94",
    "author": "Sri Manjunatha Bhagavatha",
    "publisher": "Prabhat Printers, Ltd., Mangalore",
    "info": "",
    "tags": "ಒಂದಾಣೆ ಮಾಲೆ, ಕನ್ನಡ ಸಾಹಿತ್ಯ",
    "level": "Kannada Literature",
    "authorUrl": "https://archive.org/search.php?query=creator%3AYakshagana Natakada Parampare Mathu Kruthigalu 94",
    "url": "https://archive.org/details/yakshagananataka0000srim",
    "cover": "https://archive.org/services/img/yakshagananataka0000srim"
  },
  {
    "identifier": "bharathiyakanman0000srip",
    "title": "Bharathiya Kanmanigalu (Bhaga 1) 198",
    "author": "Sri P. Ramanna Chadaga",
    "publisher": "Prabhat Printers, Ltd., Mangalore",
    "info": "",
    "tags": "ಒಂದಾಣೆ ಮಾಲೆ, ಕನ್ನಡ ಸಾಹಿತ್ಯ",
    "level": "Kannada Literature",
    "authorUrl": "https://archive.org/search.php?query=creator%3ABharathiya Kanmanigalu (Bhaga 1) 198",
    "url": "https://archive.org/details/bharathiyakanman0000srip",
    "cover": "https://archive.org/services/img/bharathiyakanman0000srip"
  },
  {
    "identifier": "kelavuupayukthas0000srib",
    "title": "Kelavu Upayuktha Salahegalu 91",
    "author": "Sri Ballkuru Subraya Adiga",
    "publisher": "Prabhat Printers, Ltd., Mangalore",
    "info": "",
    "tags": "ಒಂದಾಣೆ ಮಾಲೆ, ಕನ್ನಡ ಸಾಹಿತ್ಯ",
    "level": "Kannada Literature",
    "authorUrl": "https://archive.org/search.php?query=creator%3AKelavu Upayuktha Salahegalu 91",
    "url": "https://archive.org/details/kelavuupayukthas0000srib",
    "cover": "https://archive.org/services/img/kelavuupayukthas0000srib"
  },
  {
    "identifier": "aralidanagu570000srib",
    "title": "Aralida Nagu 57",
    "author": "Sri Ballkuru Subraya Adiga",
    "publisher": "Prabhat Printers, Ltd., Mangalore",
    "info": "",
    "tags": "ಒಂದಾಣೆ ಮಾಲೆ, ಕನ್ನಡ ಸಾಹಿತ್ಯ",
    "level": "Kannada Literature",
    "authorUrl": "https://archive.org/search.php?query=creator%3AAralida Nagu 57",
    "url": "https://archive.org/details/aralidanagu570000srib",
    "cover": "https://archive.org/services/img/aralidanagu570000srib"
  },
  {
    "identifier": "phalodayaathavag0000vidh",
    "title": "Phalodaya Athava Girija Kalyana 197",
    "author": "Vidhwan M. Gopalakrishna Bhat",
    "publisher": "Prabhat Printers, Ltd., Mangalore",
    "info": "",
    "tags": "ಒಂದಾಣೆ ಮಾಲೆ, ಕನ್ನಡ ಸಾಹಿತ್ಯ",
    "level": "Kannada Literature",
    "authorUrl": "https://archive.org/search.php?query=creator%3APhalodaya Athava Girija Kalyana 197",
    "url": "https://archive.org/details/phalodayaathavag0000vidh",
    "cover": "https://archive.org/services/img/phalodayaathavag0000vidh"
  },
  {
    "identifier": "navakailasa1230000srim",
    "title": "Nava Kailasa 123",
    "author": "Sri Maalakoda Narayana",
    "publisher": "Prabhat Printers, Ltd., Mangalore",
    "info": "",
    "tags": "ಒಂದಾಣೆ ಮಾಲೆ, ಕನ್ನಡ ಸಾಹಿತ್ಯ",
    "level": "Kannada Literature",
    "authorUrl": "https://archive.org/search.php?query=creator%3ANava Kailasa 123",
    "url": "https://archive.org/details/navakailasa1230000srim",
    "cover": "https://archive.org/services/img/navakailasa1230000srim"
  },
  {
    "identifier": "hastharekavignya0000drkk",
    "title": "Hasthareka Vignyana 97",
    "author": "Dr K. K. Kallkur",
    "publisher": "Prabhat Printers, Ltd., Mangalore",
    "info": "",
    "tags": "ಒಂದಾಣೆ ಮಾಲೆ, ಕನ್ನಡ ಸಾಹಿತ್ಯ",
    "level": "Kannada Literature",
    "authorUrl": "https://archive.org/search.php?query=creator%3AHasthareka Vignyana 97",
    "url": "https://archive.org/details/hastharekavignya0000drkk",
    "cover": "https://archive.org/services/img/hastharekavignya0000drkk"
  },
  {
    "identifier": "doctorgandijiath0000srim",
    "title": "Doctor Gandiji Athava Nisargachikithse Mathu Gandiji 80",
    "author": "Sri Marakini Shankaranarayana",
    "publisher": "Prabhat Printers, Ltd., Mangalore",
    "info": "",
    "tags": "ಒಂದಾಣೆ ಮಾಲೆ, ಕನ್ನಡ ಸಾಹಿತ್ಯ",
    "level": "Kannada Literature",
    "authorUrl": "https://archive.org/search.php?query=creator%3ADoctor Gandiji Athava Nisargachikithse Mathu Gandiji 80",
    "url": "https://archive.org/details/doctorgandijiath0000srim",
    "cover": "https://archive.org/services/img/doctorgandijiath0000srim"
  },
  {
    "identifier": "srikeshtraudupi60000kpra",
    "title": "Sri Keshtra Udupi 69",
    "author": "K. Prabhakara Rao",
    "publisher": "Prabhat Printers, Ltd., Mangalore",
    "info": "",
    "tags": "ಒಂದಾಣೆ ಮಾಲೆ, ಕನ್ನಡ ಸಾಹಿತ್ಯ",
    "level": "Kannada Literature",
    "authorUrl": "https://archive.org/search.php?query=creator%3ASri Keshtra Udupi 69",
    "url": "https://archive.org/details/srikeshtraudupi60000kpra",
    "cover": "https://archive.org/services/img/srikeshtraudupi60000kpra"
  },
  {
    "identifier": "bakthakuchela1000000sria",
    "title": "Baktha Kuchela 100",
    "author": "Sri Ambaatanaya, Mudradi",
    "publisher": "Prabhat Printers, Ltd., Mangalore",
    "info": "",
    "tags": "ಒಂದಾಣೆ ಮಾಲೆ, ಕನ್ನಡ ಸಾಹಿತ್ಯ",
    "level": "Kannada Literature",
    "authorUrl": "https://archive.org/search.php?query=creator%3ABaktha Kuchela 100",
    "url": "https://archive.org/details/bakthakuchela1000000sria",
    "cover": "https://archive.org/services/img/bakthakuchela1000000sria"
  },
  {
    "identifier": "eyugadhatenkarak0000kudp",
    "title": "E Yugadha Tenkara Kumara 102",
    "author": "Kudpi Vasudeva Shenoy",
    "publisher": "Prabhat Printers, Ltd., Mangalore",
    "info": "",
    "tags": "ಒಂದಾಣೆ ಮಾಲೆ, ಕನ್ನಡ ಸಾಹಿತ್ಯ",
    "level": "Kannada Literature",
    "authorUrl": "https://archive.org/search.php?query=creator%3AE Yugadha Tenkara Kumara 102",
    "url": "https://archive.org/details/eyugadhatenkarak0000kudp",
    "cover": "https://archive.org/services/img/eyugadhatenkarak0000kudp"
  },
  {
    "identifier": "madveavanthara100000unse",
    "title": "Madve Avanthara 106",
    "author": "",
    "publisher": "Prabhat Printers, Ltd., Mangalore",
    "info": "",
    "tags": "ಒಂದಾಣೆ ಮಾಲೆ, ಕನ್ನಡ ಸಾಹಿತ್ಯ",
    "level": "Kannada Literature",
    "authorUrl": "https://archive.org/search.php?query=creator%3AMadve Avanthara 106",
    "url": "https://archive.org/details/madveavanthara100000unse",
    "cover": "https://archive.org/services/img/madveavanthara100000unse"
  },
  {
    "identifier": "bedanamagalu1130000sriv",
    "title": "Bedana Magalu 113",
    "author": "Sri Venkataraja Punichathaya",
    "publisher": "Prabhat Printers, Ltd., Mangalore",
    "info": "",
    "tags": "ಒಂದಾಣೆ ಮಾಲೆ, ಕನ್ನಡ ಸಾಹಿತ್ಯ",
    "level": "Kannada Literature",
    "authorUrl": "https://archive.org/search.php?query=creator%3ABedana Magalu 113",
    "url": "https://archive.org/details/bedanamagalu1130000sriv",
    "cover": "https://archive.org/services/img/bedanamagalu1130000sriv"
  },
  {
    "identifier": "bedaginanadukoda0000sris",
    "title": "Bedagina Nadu-Kodagu 83",
    "author": "Sri Sripathi Rao Palimarkar",
    "publisher": "Prabhat Printers, Ltd., Mangalore",
    "info": "",
    "tags": "ಒಂದಾಣೆ ಮಾಲೆ, ಕನ್ನಡ ಸಾಹಿತ್ಯ",
    "level": "Kannada Literature",
    "authorUrl": "https://archive.org/search.php?query=creator%3ABedagina Nadu-Kodagu 83",
    "url": "https://archive.org/details/bedaginanadukoda0000sris",
    "cover": "https://archive.org/services/img/bedaginanadukoda0000sris"
  },
  {
    "identifier": "venurinagathavai0000loka",
    "title": "Venurina Gatha Vaibhava 16",
    "author": "Lokanaatha Shastri",
    "publisher": "Prabhat Printers, Ltd., Mangalore",
    "info": "",
    "tags": "ಒಂದಾಣೆ ಮಾಲೆ, ಕನ್ನಡ ಸಾಹಿತ್ಯ",
    "level": "Kannada Literature",
    "authorUrl": "https://archive.org/search.php?query=creator%3AVenurina Gatha Vaibhava 16",
    "url": "https://archive.org/details/venurinagathavai0000loka",
    "cover": "https://archive.org/services/img/venurinagathavai0000loka"
  },
  {
    "identifier": "makkalapadyagalu0000sria",
    "title": "Makkala Padyagalu 129",
    "author": "Sri Ammebala Ananthaya Navada, Vidwan",
    "publisher": "Prabhat Printers, Ltd., Mangalore",
    "info": "",
    "tags": "ಒಂದಾಣೆ ಮಾಲೆ, ಕನ್ನಡ ಸಾಹಿತ್ಯ",
    "level": "Kannada Literature",
    "authorUrl": "https://archive.org/search.php?query=creator%3AMakkala Padyagalu 129",
    "url": "https://archive.org/details/makkalapadyagalu0000sria",
    "cover": "https://archive.org/services/img/makkalapadyagalu0000sria"
  },
  {
    "identifier": "purandaradasaru10000srib",
    "title": "Purandara Dasaru 117",
    "author": "Sri B. Padmanabha Sowmayaji",
    "publisher": "Prabhat Printers, Ltd., Mangalore",
    "info": "",
    "tags": "ಒಂದಾಣೆ ಮಾಲೆ, ಕನ್ನಡ ಸಾಹಿತ್ಯ",
    "level": "Kannada Literature",
    "authorUrl": "https://archive.org/search.php?query=creator%3APurandara Dasaru 117",
    "url": "https://archive.org/details/purandaradasaru10000srib",
    "cover": "https://archive.org/services/img/purandaradasaru10000srib"
  },
  {
    "identifier": "bhakthadruva1110000subr",
    "title": "Bhaktha Druva 111",
    "author": "Subraya, Anathapura",
    "publisher": "Prabhat Printers, Ltd., Mangalore",
    "info": "",
    "tags": "ಒಂದಾಣೆ ಮಾಲೆ, ಕನ್ನಡ ಸಾಹಿತ್ಯ",
    "level": "Kannada Literature",
    "authorUrl": "https://archive.org/search.php?query=creator%3ABhaktha Druva 111",
    "url": "https://archive.org/details/bhakthadruva1110000subr",
    "cover": "https://archive.org/services/img/bhakthadruva1110000subr"
  },
  {
    "identifier": "suryanenanagesak0000srin",
    "title": "Suryane Nanage Sakshi Mathu Ethara Kathegalu 122",
    "author": "Sri N. S. Navakana, Peradala",
    "publisher": "Prabhat Printers, Ltd., Mangalore",
    "info": "",
    "tags": "ಒಂದಾಣೆ ಮಾಲೆ, ಕನ್ನಡ ಸಾಹಿತ್ಯ",
    "level": "Kannada Literature",
    "authorUrl": "https://archive.org/search.php?query=creator%3ASuryane Nanage Sakshi Mathu Ethara Kathegalu 122",
    "url": "https://archive.org/details/suryanenanagesak0000srin",
    "cover": "https://archive.org/services/img/suryanenanagesak0000srin"
  },
  {
    "identifier": "prathamachikiths0000srib",
    "title": "Prathama Chikithseya Kaipidi (FIRST AID) 96",
    "author": "Sri Boluru S. Rao",
    "publisher": "Prabhat Printers, Ltd., Mangalore",
    "info": "",
    "tags": "ಒಂದಾಣೆ ಮಾಲೆ, ಕನ್ನಡ ಸಾಹಿತ್ಯ",
    "level": "Kannada Literature",
    "authorUrl": "https://archive.org/search.php?query=creator%3APrathama Chikithseya Kaipidi (FIRST AID) 96",
    "url": "https://archive.org/details/prathamachikiths0000srib",
    "cover": "https://archive.org/services/img/prathamachikiths0000srib"
  },
  {
    "identifier": "sathihrundaathav0000srik",
    "title": "Sathi Hrunda Athava Jalandhara Vadhe 86",
    "author": "Sri K. Subashchandra Shenoy",
    "publisher": "Prabhat Printers, Ltd., Mangalore",
    "info": "",
    "tags": "ಒಂದಾಣೆ ಮಾಲೆ, ಕನ್ನಡ ಸಾಹಿತ್ಯ",
    "level": "Kannada Literature",
    "authorUrl": "https://archive.org/search.php?query=creator%3ASathi Hrunda Athava Jalandhara Vadhe 86",
    "url": "https://archive.org/details/sathihrundaathav0000srik",
    "cover": "https://archive.org/services/img/sathihrundaathav0000srik"
  },
  {
    "identifier": "swathantrya980000sris",
    "title": "Swathantrya 98",
    "author": "Sri Surendra Kumara Malhotra",
    "publisher": "Prabhat Printers, Ltd., Mangalore",
    "info": "",
    "tags": "ಒಂದಾಣೆ ಮಾಲೆ, ಕನ್ನಡ ಸಾಹಿತ್ಯ",
    "level": "Kannada Literature",
    "authorUrl": "https://archive.org/search.php?query=creator%3ASwathantrya 98",
    "url": "https://archive.org/details/swathantrya980000sris",
    "cover": "https://archive.org/services/img/swathantrya980000sris"
  },
  {
    "identifier": "chutabittadhitta0000drsp",
    "title": "Chuta Bitta Dhitta 59",
    "author": "Dr. S. P. Bhat",
    "publisher": "Prabhat Printers, Ltd., Mangalore",
    "info": "",
    "tags": "ಒಂದಾಣೆ ಮಾಲೆ, ಕನ್ನಡ ಸಾಹಿತ್ಯ",
    "level": "Kannada Literature",
    "authorUrl": "https://archive.org/search.php?query=creator%3AChuta Bitta Dhitta 59",
    "url": "https://archive.org/details/chutabittadhitta0000drsp",
    "cover": "https://archive.org/services/img/chutabittadhitta0000drsp"
  },
  {
    "identifier": "jagathinavignayn0000srit",
    "title": "Jagathina Vignaynigalu 107",
    "author": "Sri T. Chandraraja Shetty",
    "publisher": "Prabhat Printers, Ltd., Mangalore",
    "info": "",
    "tags": "ಒಂದಾಣೆ ಮಾಲೆ, ಕನ್ನಡ ಸಾಹಿತ್ಯ",
    "level": "Kannada Literature",
    "authorUrl": "https://archive.org/search.php?query=creator%3AJagathina Vignaynigalu 107",
    "url": "https://archive.org/details/jagathinavignayn0000srit",
    "cover": "https://archive.org/services/img/jagathinavignayn0000srit"
  },
  {
    "identifier": "bharathiyaswatha0000srim",
    "title": "Bharathiya Swathantrya Sangrama 99",
    "author": "Sri M. Raghunandana Rao",
    "publisher": "Prabhat Printers, Ltd., Mangalore",
    "info": "",
    "tags": "ಒಂದಾಣೆ ಮಾಲೆ, ಕನ್ನಡ ಸಾಹಿತ್ಯ",
    "level": "Kannada Literature",
    "authorUrl": "https://archive.org/search.php?query=creator%3ABharathiya Swathantrya Sangrama 99",
    "url": "https://archive.org/details/bharathiyaswatha0000srim",
    "cover": "https://archive.org/services/img/bharathiyaswatha0000srim"
  },
  {
    "identifier": "homiyopathichiki0000srib",
    "title": "Homiyopathi Chikithsara 93",
    "author": "Sri Boluru S. Rao",
    "publisher": "Prabhat Printers, Ltd., Mangalore",
    "info": "",
    "tags": "ಒಂದಾಣೆ ಮಾಲೆ, ಕನ್ನಡ ಸಾಹಿತ್ಯ",
    "level": "Kannada Literature",
    "authorUrl": "https://archive.org/search.php?query=creator%3AHomiyopathi Chikithsara 93",
    "url": "https://archive.org/details/homiyopathichiki0000srib",
    "cover": "https://archive.org/services/img/homiyopathichiki0000srib"
  },
  {
    "identifier": "abhiganyanashaku0000srik",
    "title": "Abhiganyana Shakunthaladali Lokaneethi 92",
    "author": "Sri K. L. N. Upadhaya",
    "publisher": "Prabhat Printers, Ltd., Mangalore",
    "info": "",
    "tags": "ಒಂದಾಣೆ ಮಾಲೆ, ಕನ್ನಡ ಸಾಹಿತ್ಯ",
    "level": "Kannada Literature",
    "authorUrl": "https://archive.org/search.php?query=creator%3AAbhiganyana Shakunthaladali Lokaneethi 92",
    "url": "https://archive.org/details/abhiganyanashaku0000srik",
    "cover": "https://archive.org/services/img/abhiganyanashaku0000srik"
  },
  {
    "identifier": "ogatugalagonchal0000drsp",
    "title": "Ogatugala Gonchalu 104",
    "author": "Dr. S. P. Bhat",
    "publisher": "Prabhat Printers, Ltd., Mangalore",
    "info": "",
    "tags": "ಒಂದಾಣೆ ಮಾಲೆ, ಕನ್ನಡ ಸಾಹಿತ್ಯ",
    "level": "Kannada Literature",
    "authorUrl": "https://archive.org/search.php?query=creator%3AOgatugala Gonchalu 104",
    "url": "https://archive.org/details/ogatugalagonchal0000drsp",
    "cover": "https://archive.org/services/img/ogatugalagonchal0000drsp"
  },
  {
    "identifier": "karunemathuethar0000srib",
    "title": "Karune Mathu Ethara Kathegalu 68",
    "author": "Sri Ballkuru Subraya Adiga",
    "publisher": "Prabhat Printers, Ltd., Mangalore",
    "info": "",
    "tags": "ಒಂದಾಣೆ ಮಾಲೆ, ಕನ್ನಡ ಸಾಹಿತ್ಯ",
    "level": "Kannada Literature",
    "authorUrl": "https://archive.org/search.php?query=creator%3AKarune Mathu Ethara Kathegalu 68",
    "url": "https://archive.org/details/karunemathuethar0000srib",
    "cover": "https://archive.org/services/img/karunemathuethar0000srib"
  },
  {
    "identifier": "veeragranikarna10000amem",
    "title": "Veeragrani - Karna 121",
    "author": "Amembala Ananthaya Navada, Vidhwan",
    "publisher": "Prabhat Printers, Ltd., Mangalore",
    "info": "",
    "tags": "ಒಂದಾಣೆ ಮಾಲೆ, ಕನ್ನಡ ಸಾಹಿತ್ಯ",
    "level": "Kannada Literature",
    "authorUrl": "https://archive.org/search.php?query=creator%3AVeeragrani - Karna 121",
    "url": "https://archive.org/details/veeragranikarna10000amem",
    "cover": "https://archive.org/services/img/veeragranikarna10000amem"
  },
  {
    "identifier": "nammaahara1150000srik",
    "title": "Namma Ahara 115",
    "author": "Sri K. C. Vyedyar",
    "publisher": "Prabhat Printers, Ltd., Mangalore",
    "info": "",
    "tags": "ಒಂದಾಣೆ ಮಾಲೆ, ಕನ್ನಡ ಸಾಹಿತ್ಯ",
    "level": "Kannada Literature",
    "authorUrl": "https://archive.org/search.php?query=creator%3ANamma Ahara 115",
    "url": "https://archive.org/details/nammaahara1150000srik",
    "cover": "https://archive.org/services/img/nammaahara1150000srik"
  },
  {
    "identifier": "tathsamathadbava0000sric",
    "title": "Tathsama-Thadbava Kosha 201",
    "author": "Sri Chandrashekar Chadaga",
    "publisher": "Prabhat Printers, Ltd., Mangalore",
    "info": "",
    "tags": "ಒಂದಾಣೆ ಮಾಲೆ, ಕನ್ನಡ ಸಾಹಿತ್ಯ",
    "level": "Kannada Literature",
    "authorUrl": "https://archive.org/search.php?query=creator%3ATathsama-Thadbava Kosha 201",
    "url": "https://archive.org/details/tathsamathadbava0000sric",
    "cover": "https://archive.org/services/img/tathsamathadbava0000sric"
  },
  {
    "identifier": "yamalokayathreat0000sriv",
    "title": "Yamaloka Yathre Athava Nachiketha 205",
    "author": "Sri Venkataraja Punimchathaya",
    "publisher": "Prabhat Printers, Ltd., Mangalore",
    "info": "",
    "tags": "ಒಂದಾಣೆ ಮಾಲೆ, ಕನ್ನಡ ಸಾಹಿತ್ಯ",
    "level": "Kannada Literature",
    "authorUrl": "https://archive.org/search.php?query=creator%3AYamaloka Yathre Athava Nachiketha 205",
    "url": "https://archive.org/details/yamalokayathreat0000sriv",
    "cover": "https://archive.org/services/img/yamalokayathreat0000sriv"
  },
  {
    "identifier": "haridasapavanjel0000srib",
    "title": "Haridasa Pavanje Lakshminarayanavara Jeevana Charitre Mathu Kelavu Bajanageethegalu 206",
    "author": "Sri Bele Bhujanga Rao",
    "publisher": "Prabhat Printers, Ltd., Mangalore",
    "info": "",
    "tags": "ಒಂದಾಣೆ ಮಾಲೆ, ಕನ್ನಡ ಸಾಹಿತ್ಯ",
    "level": "Kannada Literature",
    "authorUrl": "https://archive.org/search.php?query=creator%3AHaridasa Pavanje Lakshminarayanavara Jeevana Charitre Mathu Kelavu Bajanageethegalu 206",
    "url": "https://archive.org/details/haridasapavanjel0000srib",
    "cover": "https://archive.org/services/img/haridasapavanjel0000srib"
  },
  {
    "identifier": "saleema2040000vidh",
    "title": "Saleema 204",
    "author": "Vidhwan M. Gopalakrishna Bhat",
    "publisher": "Prabhat Printers, Ltd., Mangalore",
    "info": "",
    "tags": "ಒಂದಾಣೆ ಮಾಲೆ, ಕನ್ನಡ ಸಾಹಿತ್ಯ",
    "level": "Kannada Literature",
    "authorUrl": "https://archive.org/search.php?query=creator%3ASaleema 204",
    "url": "https://archive.org/details/saleema2040000vidh",
    "cover": "https://archive.org/services/img/saleema2040000vidh"
  },
  {
    "identifier": "karnatakakavicha0000srib",
    "title": "Karnataka Kavi Charithre 112",
    "author": "Sri. B. Eshwaraya",
    "publisher": "Prabhat Printers, Ltd., Mangalore",
    "info": "",
    "tags": "ಒಂದಾಣೆ ಮಾಲೆ, ಕನ್ನಡ ಸಾಹಿತ್ಯ",
    "level": "Kannada Literature",
    "authorUrl": "https://archive.org/search.php?query=creator%3AKarnataka Kavi Charithre 112",
    "url": "https://archive.org/details/karnatakakavicha0000srib",
    "cover": "https://archive.org/services/img/karnatakakavicha0000srib"
  },
  {
    "identifier": "panditajavaharla0000kudp",
    "title": "Pandita Javaharlal Neharu 67",
    "author": "Kudpi Vasudeva Shenoy",
    "publisher": "Prabhat Printers, Ltd., Mangalore",
    "info": "",
    "tags": "ಒಂದಾಣೆ ಮಾಲೆ, ಕನ್ನಡ ಸಾಹಿತ್ಯ",
    "level": "Kannada Literature",
    "authorUrl": "https://archive.org/search.php?query=creator%3APandita Javaharlal Neharu 67",
    "url": "https://archive.org/details/panditajavaharla0000kudp",
    "cover": "https://archive.org/services/img/panditajavaharla0000kudp"
  },
  {
    "identifier": "bakthavani610000govi",
    "title": "Bakthavani 61",
    "author": "Govinda Pai",
    "publisher": "Prabhat Printers, Ltd., Mangalore",
    "info": "",
    "tags": "ಒಂದಾಣೆ ಮಾಲೆ, ಕನ್ನಡ ಸಾಹಿತ್ಯ",
    "level": "Kannada Literature",
    "authorUrl": "https://archive.org/search.php?query=creator%3ABakthavani 61",
    "url": "https://archive.org/details/bakthavani610000govi",
    "cover": "https://archive.org/services/img/bakthavani610000govi"
  },
  {
    "identifier": "devarasamrajyada0000sris",
    "title": "Devara Samrajyadali 75",
    "author": "Sri S. N. Navakanaq",
    "publisher": "Prabhat Printers, Ltd., Mangalore",
    "info": "",
    "tags": "ಒಂದಾಣೆ ಮಾಲೆ, ಕನ್ನಡ ಸಾಹಿತ್ಯ",
    "level": "Kannada Literature",
    "authorUrl": "https://archive.org/search.php?query=creator%3ADevara Samrajyadali 75",
    "url": "https://archive.org/details/devarasamrajyada0000sris",
    "cover": "https://archive.org/services/img/devarasamrajyada0000sris"
  },
  {
    "identifier": "doctorarogyam630000chak",
    "title": "Doctor Arogyam 63",
    "author": "Chakaravatrhi Sri Rajagopalachar",
    "publisher": "Prabhat Printers, Ltd., Mangalore",
    "info": "",
    "tags": "ಒಂದಾಣೆ ಮಾಲೆ, ಕನ್ನಡ ಸಾಹಿತ್ಯ",
    "level": "Kannada Literature",
    "authorUrl": "https://archive.org/search.php?query=creator%3ADoctor Arogyam 63",
    "url": "https://archive.org/details/doctorarogyam630000chak",
    "cover": "https://archive.org/services/img/doctorarogyam630000chak"
  },
  {
    "identifier": "narishvararuekan0000kudp",
    "title": "Narishvararu (Ekanka Prasanna) 2",
    "author": "Kudpi Vasudev Shenoy",
    "publisher": "Prabhat Printers, Ltd., Mangalore",
    "info": "",
    "tags": "ಒಂದಾಣೆ ಮಾಲೆ, ಕನ್ನಡ ಸಾಹಿತ್ಯ",
    "level": "Kannada Literature",
    "authorUrl": "https://archive.org/search.php?query=creator%3ANarishvararu (Ekanka Prasanna) 2",
    "url": "https://archive.org/details/narishvararuekan0000kudp",
    "cover": "https://archive.org/services/img/narishvararuekan0000kudp"
  },
  {
    "identifier": "jarasandavade660000sria",
    "title": "Jarasanda Vade 66",
    "author": "Sri A. V. Mayya",
    "publisher": "Prabhat Printers, Ltd., Mangalore",
    "info": "",
    "tags": "ಒಂದಾಣೆ ಮಾಲೆ, ಕನ್ನಡ ಸಾಹಿತ್ಯ",
    "level": "Kannada Literature",
    "authorUrl": "https://archive.org/search.php?query=creator%3AJarasanda Vade 66",
    "url": "https://archive.org/details/jarasandavade660000sria",
    "cover": "https://archive.org/services/img/jarasandavade660000sria"
  },
  {
    "identifier": "amruthavani780000srim",
    "title": "Amruthavani 78",
    "author": "Sri M. Sridhar Kini",
    "publisher": "Prabhat Printers, Ltd., Mangalore",
    "info": "",
    "tags": "ಒಂದಾಣೆ ಮಾಲೆ, ಕನ್ನಡ ಸಾಹಿತ್ಯ",
    "level": "Kannada Literature",
    "authorUrl": "https://archive.org/search.php?query=creator%3AAmruthavani 78",
    "url": "https://archive.org/details/amruthavani780000srim",
    "cover": "https://archive.org/services/img/amruthavani780000srim"
  },
  {
    "identifier": "nammanatakagalu80000srim",
    "title": "Namma Natakagalu 89",
    "author": "Sri M. S. Achar",
    "publisher": "Prabhat Printers, Ltd., Mangalore",
    "info": "",
    "tags": "ಒಂದಾಣೆ ಮಾಲೆ, ಕನ್ನಡ ಸಾಹಿತ್ಯ",
    "level": "Kannada Literature",
    "authorUrl": "https://archive.org/search.php?query=creator%3ANamma Natakagalu 89",
    "url": "https://archive.org/details/nammanatakagalu80000srim",
    "cover": "https://archive.org/services/img/nammanatakagalu80000srim"
  },
  {
    "identifier": "jaathakakathegal0000srim",
    "title": "Jaathaka Kathegalu 30",
    "author": "Sri. M. Subrayan",
    "publisher": "Prabhat Printers, Ltd., Mangalore",
    "info": "",
    "tags": "ಒಂದಾಣೆ ಮಾಲೆ, ಕನ್ನಡ ಸಾಹಿತ್ಯ",
    "level": "Kannada Literature",
    "authorUrl": "https://archive.org/search.php?query=creator%3AJaathaka Kathegalu 30",
    "url": "https://archive.org/details/jaathakakathegal0000srim",
    "cover": "https://archive.org/services/img/jaathakakathegal0000srim"
  },
  {
    "identifier": "niraparadhi600000sric",
    "title": "Niraparadhi 60",
    "author": "Sri Chakravarthi Rajagopaalachari",
    "publisher": "Prabhat Printers, Ltd., Mangalore",
    "info": "",
    "tags": "ಒಂದಾಣೆ ಮಾಲೆ, ಕನ್ನಡ ಸಾಹಿತ್ಯ",
    "level": "Kannada Literature",
    "authorUrl": "https://archive.org/search.php?query=creator%3ANiraparadhi 60",
    "url": "https://archive.org/details/niraparadhi600000sric",
    "cover": "https://archive.org/services/img/niraparadhi600000sric"
  },
  {
    "identifier": "punarujeevana950000srig",
    "title": "Punarujeevana 95",
    "author": "Sri Govinda Bhat, Shedigumme",
    "publisher": "Prabhat Printers, Ltd., Mangalore",
    "info": "",
    "tags": "ಒಂದಾಣೆ ಮಾಲೆ, ಕನ್ನಡ ಸಾಹಿತ್ಯ",
    "level": "Kannada Literature",
    "authorUrl": "https://archive.org/search.php?query=creator%3APunarujeevana 95",
    "url": "https://archive.org/details/punarujeevana950000srig",
    "cover": "https://archive.org/services/img/punarujeevana950000srig"
  },
  {
    "identifier": "nammahabbagalu120000shya",
    "title": "Namma Habbagalu 120",
    "author": "Shyama, Putturu",
    "publisher": "Prabhat Printers, Ltd., Mangalore",
    "info": "",
    "tags": "ಒಂದಾಣೆ ಮಾಲೆ, ಕನ್ನಡ ಸಾಹಿತ್ಯ",
    "level": "Kannada Literature",
    "authorUrl": "https://archive.org/search.php?query=creator%3ANamma Habbagalu 120",
    "url": "https://archive.org/details/nammahabbagalu120000shya",
    "cover": "https://archive.org/services/img/nammahabbagalu120000shya"
  },
  {
    "identifier": "urahoushadagalum0000srib",
    "title": "Ura - Houshadagalu Mathu Ethara Upayuktha Suchanegalu 105",
    "author": "Sri Bholuru S. Rao",
    "publisher": "Prabhat Printers, Ltd., Mangalore",
    "info": "",
    "tags": "ಒಂದಾಣೆ ಮಾಲೆ, ಕನ್ನಡ ಸಾಹಿತ್ಯ",
    "level": "Kannada Literature",
    "authorUrl": "https://archive.org/search.php?query=creator%3AUra - Houshadagalu Mathu Ethara Upayuktha Suchanegalu 105",
    "url": "https://archive.org/details/urahoushadagalum0000srib",
    "cover": "https://archive.org/services/img/urahoushadagalum0000srib"
  },
  {
    "identifier": "karntikanteerava0000sris",
    "title": "Karnti Kanteerava Bhagath Sing 76",
    "author": "Sri Sathyasharya Kamat",
    "publisher": "Prabhat Printers, Ltd., Mangalore",
    "info": "",
    "tags": "ಒಂದಾಣೆ ಮಾಲೆ, ಕನ್ನಡ ಸಾಹಿತ್ಯ",
    "level": "Kannada Literature",
    "authorUrl": "https://archive.org/search.php?query=creator%3AKarnti Kanteerava Bhagath Sing 76",
    "url": "https://archive.org/details/karntikanteerava0000sris",
    "cover": "https://archive.org/services/img/karntikanteerava0000sris"
  },
  {
    "identifier": "bharathadasangee0000hsun",
    "title": "Bharathada Sangeetha Jyothigalu 128",
    "author": "H. Sundararama Rao",
    "publisher": "Prabhat Printers, Ltd., Mangalore",
    "info": "",
    "tags": "ಒಂದಾಣೆ ಮಾಲೆ, ಕನ್ನಡ ಸಾಹಿತ್ಯ",
    "level": "Kannada Literature",
    "authorUrl": "https://archive.org/search.php?query=creator%3ABharathada Sangeetha Jyothigalu 128",
    "url": "https://archive.org/details/bharathadasangee0000hsun",
    "cover": "https://archive.org/services/img/bharathadasangee0000hsun"
  },
  {
    "identifier": "uattarakannadaje0000sriv",
    "title": "Uattara Kannada Jeleya Yakshagana Kalavidaru 74",
    "author": "Sri Vigneshwara Sharma Taddalase, Sirsi",
    "publisher": "Prabhat Printers, Ltd., Mangalore",
    "info": "",
    "tags": "ಒಂದಾಣೆ ಮಾಲೆ, ಕನ್ನಡ ಸಾಹಿತ್ಯ",
    "level": "Kannada Literature",
    "authorUrl": "https://archive.org/search.php?query=creator%3AUattara Kannada Jeleya Yakshagana Kalavidaru 74",
    "url": "https://archive.org/details/uattarakannadaje0000sriv",
    "cover": "https://archive.org/services/img/uattarakannadaje0000sriv"
  },
  {
    "identifier": "dwaraka1270000srig",
    "title": "Dwaraka 127",
    "author": "Sri Gumdi Mahabala Bhat",
    "publisher": "Prabhat Printers, Ltd., Mangalore",
    "info": "",
    "tags": "ಒಂದಾಣೆ ಮಾಲೆ, ಕನ್ನಡ ಸಾಹಿತ್ಯ",
    "level": "Kannada Literature",
    "authorUrl": "https://archive.org/search.php?query=creator%3ADwaraka 127",
    "url": "https://archive.org/details/dwaraka1270000srig",
    "cover": "https://archive.org/services/img/dwaraka1270000srig"
  }
]
}
